usmu_py/__init__.py
usmu_py/example_iv_point.py
usmu_py/example_iv_sweep.py
usmu_py/smu.py
usmu_py-1.0.0.dist-info/METADATA
usmu_py-1.0.0.dist-info/WHEEL
usmu_py-1.0.0.dist-info/top_level.txt
usmu_py-1.0.0.dist-info/RECORD
