Metadata-Version: 2.1
Name: usmu_py
Version: 1.0.0
Summary: A simple Python library for controlling the uSMU source-measure unit
Home-page: https://github.com/Undalogic/usmu_py
Author: Joel Troughton
Author-email: joel.troughton@undalogic.com
Classifier: Programming Language :: Python :: 3
Classifier: Operating System :: OS Independent
Requires-Python: >=3.6
Requires-Dist: pyserial>=3.0
Requires-Dist: numpy>=1.18
